gnotify/___init__.py
gnotify/__main__.py
gnotify/gnotify.py
gnotify-0.1.0.dist-info/LICENSE
gnotify-0.1.0.dist-info/METADATA
gnotify-0.1.0.dist-info/WHEEL
gnotify-0.1.0.dist-info/entry_points.txt
gnotify-0.1.0.dist-info/top_level.txt
gnotify-0.1.0.dist-info/RECORD
