Metadata-Version: 2.1
Name: gnotify
Version: 0.1.0
Summary: Get notified on your Google Home device from text-to-speech
Home-page: UNKNOWN
Author: Benoît Bourgeois
Author-email: bierdok@gmail.com
License: UNKNOWN
Platform: UNKNOWN
Classifier: Programming Language :: Python :: 3
Classifier: License :: OSI Approved :: MIT License
Classifier: Operating System :: OS Independent
Requires-Dist: cachier (==1.2.4)
Requires-Dist: pychromecast (==2.3.0)
Requires-Dist: pymongo (==3.7.2)
